async7zip/__init__.py
async7zip/async7zip.py
async7zip-1.0.1.dist-info/LICENSE
async7zip-1.0.1.dist-info/METADATA
async7zip-1.0.1.dist-info/WHEEL
async7zip-1.0.1.dist-info/top_level.txt
async7zip-1.0.1.dist-info/RECORD
