Metadata-Version: 2.1
Name: async7zip
Version: 1.0.1
Home-page: https://github.com/keklick1337/async7zip
Author: Vladislav Tislenko
Author-email: keklick1337@gmail.com
Project-URL: Documentation, https://github.com/keklick1337/async7zip
Project-URL: Bug Reports, https://github.com/keklick1337/async7zip/issues
Project-URL: Source Code, https://github.com/keklick1337/async7zip
Requires-Python: >=3.9
License-File: LICENSE
